database/__init__.py
database/light_orm.py
database/s3helper.py
io/__init__.py
io/logger.py
pandas/__init__.py
pandas/pd_orm.py
plot/__init__.py
plot/plotly_express.py
plot/seaborn.py
timeseries/__init__.py
moyu123-0.0.2.dist-info/METADATA
moyu123-0.0.2.dist-info/WHEEL
moyu123-0.0.2.dist-info/top_level.txt
moyu123-0.0.2.dist-info/RECORD
