Metadata-Version: 2.1
Name: moyu123
Version: 0.0.2
Summary: python常用工具集
Home-page: UNKNOWN
Author: moyu123
License: UNKNOWN
Platform: UNKNOWN
Classifier: Programming Language :: Python :: 3
Classifier: License :: OSI Approved :: MIT License
Classifier: Operating System :: OS Independent
